markdownish-0.1.2.dist-info/METADATA
markdownish-0.1.2.dist-info/WHEEL
markdownish-0.1.2.dist-info/licenses/LICENSE
markdownish/__init__.py
markdownish/markdownish.cpython-313-x86_64-linux-gnu.so
markdownish-0.1.2.dist-info/RECORD
