Metadata-Version: 2.4
Name: markdownish
Version: 0.1.2
Classifier: Programming Language :: Rust
Classifier: Programming Language :: Python :: 3
License-File: LICENSE
Summary: Render Markdown-ish to Signal-friendly text and textStyles (usable with signal-cli)
Author: markdownish
License: MIT OR Apache-2.0
Requires-Python: >=3.8
